langforge/__init__.py
langforge/main.py
langforge/bin/langforge-linux-amd64
langforge/bin/langforge-linux-arm64
langforge/bin/langforge-macos-amd64
langforge/bin/langforge-macos-arm64
langforge/bin/langforge-windows-amd64.exe
langforge_ai-0.1.6.dist-info/METADATA
langforge_ai-0.1.6.dist-info/WHEEL
langforge_ai-0.1.6.dist-info/entry_points.txt
langforge_ai-0.1.6.dist-info/top_level.txt
langforge_ai-0.1.6.dist-info/RECORD
