Metadata-Version: 2.1
Name: langforge-ai
Version: 0.1.6
Summary: A Toolkit for Creating and Deploying LangChain Apps
Home-page: https://github.com/mme/langforge
Author: Markus Ecker
Author-email: markus.ecker@gmail.com
Classifier: Development Status :: 3 - Alpha
Classifier: Intended Audience :: Developers
Classifier: License :: OSI Approved :: MIT License
Classifier: Operating System :: OS Independent
Classifier: Programming Language :: Python :: 3
Classifier: Programming Language :: Python :: 3.6
Classifier: Programming Language :: Python :: 3.7
Classifier: Programming Language :: Python :: 3.8
Classifier: Programming Language :: Python :: 3.9
Requires-Python: >=3.6
